rackio_AI/__init__.py
rackio_AI/_singleton.py
rackio_AI/_temporal.py
rackio_AI/core.py
rackio_AI/api/__init__.py
rackio_AI/data/__init__.py
rackio_AI/data/get_pathname_data.py
rackio_AI/data/Leak/Leak01.tpl
rackio_AI/data/Leak/Leak02.tpl
rackio_AI/data/csv/Hysys/hysys.csv
rackio_AI/data/csv/VMGSim/vmgsim.csv
rackio_AI/data/csv/standard/username-password-recovery-code.csv
rackio_AI/data/pkl_files/test_data.pkl
rackio_AI/data_analysis/__init__.py
rackio_AI/data_analysis/data_analysis_core.py
rackio_AI/data_analysis/noise.py
rackio_AI/data_analysis/outliers.py
rackio_AI/decorators/__init__.py
rackio_AI/decorators/deco.py
rackio_AI/decorators/typeCheckedAttribute.py
rackio_AI/decorators/validations.py
rackio_AI/decorators/wavelets.py
rackio_AI/managers/__init__.py
rackio_AI/managers/data_analysis.py
rackio_AI/managers/managers_core.py
rackio_AI/managers/models.py
rackio_AI/managers/preprocess.py
rackio_AI/models/__init__.py
rackio_AI/models/classification.py
rackio_AI/models/ensemble.py
rackio_AI/models/gaussian_noise.py
rackio_AI/models/lstm.py
rackio_AI/models/lstm_layer.py
rackio_AI/models/models_core.py
rackio_AI/models/observer.py
rackio_AI/models/scaler.py
rackio_AI/optimization/__init__.py
rackio_AI/optimization/optimization_core.py
rackio_AI/pipeline/__init__.py
rackio_AI/pipeline/pipeline_core.py
rackio_AI/preprocessing/__init__.py
rackio_AI/preprocessing/feature_extraction.py
rackio_AI/preprocessing/feature_selection.py
rackio_AI/preprocessing/kalman_filter.py
rackio_AI/preprocessing/preprocessing_core.py
rackio_AI/preprocessing/scaler.py
rackio_AI/preprocessing/splitter.py
rackio_AI/preprocessing/synthetic_data.py
rackio_AI/preprocessing/synthetic_data_base.py
rackio_AI/readers/__init__.py
rackio_AI/readers/readers_core.py
rackio_AI/readers/_csv_/__init__.py
rackio_AI/readers/_csv_/csv_core.py
rackio_AI/readers/_csv_/json/csv_options.json
rackio_AI/readers/_csv_/json/hysys_options.json
rackio_AI/readers/_csv_/json/vmgsim_options.json
RackioAI-0.3.2.dist-info/LICENSE
RackioAI-0.3.2.dist-info/METADATA
RackioAI-0.3.2.dist-info/WHEEL
RackioAI-0.3.2.dist-info/top_level.txt
RackioAI-0.3.2.dist-info/RECORD
