Metadata-Version: 2.1
Name: RackioAI
Version: 0.3.2
Summary: A Rackio extension for AI models development
Home-page: https://github.com/crivero7/RackioAI
Author: Carlos Rivero
Author-email: cdrr.rivero@gmail.com
License: MIT
Classifier: Programming Language :: Python :: 3
Classifier: License :: OSI Approved :: MIT License
Classifier: Operating System :: OS Independent
License-File: LICENSE
Requires-Dist: pyxlsb (==1.0.8)
Requires-Dist: odfpy (==1.4.1)
Requires-Dist: openpyxl (==3.0.6)
Requires-Dist: xlrd (==1.2.0)
Requires-Dist: seaborn (==0.11.1)
Requires-Dist: scikit-learn (==1.0.2)
Requires-Dist: statsmodels (==0.13.1)
Requires-Dist: easy-deco (==0.1.2)
Requires-Dist: Pillow (==9.0.0)
Requires-Dist: tensorflow (==2.9.0)
Requires-Dist: tensorflow-probability (==0.15.0)
Requires-Dist: PyWavelets (==1.4.1)
Requires-Dist: plotly (==4.8.0)
Requires-Dist: pandas (==1.5.3)
